flakeframe/__init__.py
flakeframe/geocode.py
flakeframe/geocode_nominatim_old.py
flakeframe/input.py
flakeframe/main.py
flakeframe/map.py
flakeframe/mapview.py
flakeframe/theme.py
flakeframe/ui.py
flakeframe/ui.txt
flakeframe/weather.py
flakeframe-0.1.3.dist-info/licenses/LICENSE
flakeframe-0.1.3.dist-info/WHEEL
flakeframe-0.1.3.dist-info/entry_points.txt
flakeframe-0.1.3.dist-info/METADATA
flakeframe-0.1.3.dist-info/RECORD
