Metadata-Version: 2.4
Name: flakeframe
Version: 0.1.3
Summary: Command line weather app with a fancy map display
License-Expression: GPL-3.0-only
License-File: LICENSE
Requires-Dist: py-staticmaps>=0.4.0
Requires-Dist: pillow>=12.0.0
Requires-Dist: img2unicode>=0.1a11
Requires-Python: >=3.12
